{
  "project_info": {
    "project_number": "1013298687679",
    "project_id": "miappfirebase-c2f1e",
    "storage_bucket": "miappfirebase-c2f1e.firebasestorage.app"
  },
  "client": [
    {
      "client_info": {
        "mobilesdk_app_id": "1:1013298687679:android:5ee21caee721c17359200a",
        "android_client_info": {
          "package_name": "com.example.mi_app_firebase"
        }
      },
      "oauth_client": [],
      "api_key": [
        {
          "current_key": "AIzaSyB5-8CRlTAHu_vy2btuwL8BdUjwUz74b1U"
        }
      ],
      "services": {
        "appinvite_service": {
          "other_platform_oauth_client": []
        }
      }
    }
  ],
  "configuration_version": "1"
}